think_ai/__init__.py
think_ai/cli.py
think_ai/client.py
think_ai/types.py
thinkai_quantum-1.0.5.dist-info/licenses/LICENSE
thinkai_quantum-1.0.5.dist-info/METADATA
thinkai_quantum-1.0.5.dist-info/WHEEL
thinkai_quantum-1.0.5.dist-info/entry_points.txt
thinkai_quantum-1.0.5.dist-info/top_level.txt
thinkai_quantum-1.0.5.dist-info/RECORD
